data/lsstCamera.h5
data/lsstComCamCamera.h5
notebooks/Alerts.ipynb
notebooks/ConsDB.ipynb
notebooks/Demo.ipynb
notebooks/ScriptQueue.ipynb
notebooks/Snapshots.ipynb
rubin_nights/__init__.py
rubin_nights/augment_visits.py
rubin_nights/connections.py
rubin_nights/consdb_query.py
rubin_nights/dayobs_utils.py
rubin_nights/influx_query.py
rubin_nights/lfa_data.py
rubin_nights/logging_query.py
rubin_nights/observatory_status.py
rubin_nights/plot_utils.py
rubin_nights/rubin_scheduler_addons.py
rubin_nights/rubin_sim_addons.py
rubin_nights/scriptqueue.py
rubin_nights/scriptqueue_formatting.py
rubin_nights/targets_and_visits.py
rubin_nights/ts_xml_enums.py
rubin_nights-0.10.0.dist-info/licenses/LICENSE
scripts/make_opsim.py
scripts/night_story.py
tests/test_connections.py
tests/test_utils.py
tests/data/dummy_token
rubin_nights-0.10.0.dist-info/METADATA
rubin_nights-0.10.0.dist-info/WHEEL
rubin_nights-0.10.0.dist-info/top_level.txt
rubin_nights-0.10.0.dist-info/RECORD
