Metadata-Version: 2.4
Name: rubin_nights
Version: 0.10.0
Summary: Tools to access Rubin nightly observing data
License: GPL
Project-URL: documentation, https://rubin-nights.lsst.io
Project-URL: repository, https://github.com/lsst-sims/rubin_nights
Classifier: Intended Audience :: Science/Research
Classifier: Operating System :: OS Independent
Classifier: Programming Language :: Python :: 3
Classifier: Programming Language :: Python :: 3.10
Classifier: Programming Language :: Python :: 3.11
Classifier: Programming Language :: Python :: 3.12
Classifier: Programming Language :: Python :: 3.13
Classifier: Topic :: Scientific/Engineering :: Astronomy
License-File: LICENSE
Requires-Dist: astropy
Requires-Dist: astroplan
Requires-Dist: httpx
Requires-Dist: matplotlib
Requires-Dist: numpy
Requires-Dist: pandas
Requires-Dist: pyvo
Requires-Dist: pyyaml
Provides-Extra: rubin
Requires-Dist: healpy; extra == "rubin"
Requires-Dist: lsst-resources; extra == "rubin"
Requires-Dist: psycopg; extra == "rubin"
Requires-Dist: rubin-scheduler>=3.18; extra == "rubin"
Requires-Dist: rubin-sim; extra == "rubin"
Requires-Dist: sqlalchemy; extra == "rubin"
Provides-Extra: test
Requires-Dist: pytest; extra == "test"
Requires-Dist: black; extra == "test"
Requires-Dist: ruff; extra == "test"
Requires-Dist: isort; extra == "test"
Requires-Dist: pytest-cov; extra == "test"
Provides-Extra: dev
Requires-Dist: documenteer[guide]; extra == "dev"
Dynamic: license-file
